config/__init__.py
config/cache.py
config/common_env.py
config/constants.py
config/global_vaiables_enum.py
data_digitization-0.1.0.dist-info/METADATA
data_digitization-0.1.0.dist-info/WHEEL
data_digitization-0.1.0.dist-info/top_level.txt
data_digitization-0.1.0.dist-info/RECORD
