Metadata-Version: 2.1
Name: data_digitization
Version: 0.1.0
Summary: This SDK is for Data Digitization
Author: Sushree Sonali Panda
Author-email: sushree.panda@zs.com
Classifier: Programming Language :: Python :: 3
Classifier: License :: OSI Approved :: MIT License
Classifier: Operating System :: OS Independent
Requires-Python: >=3.6
Requires-Dist: fastapi ==0.96.0
Requires-Dist: fastjsonschema ==2.15.3
Requires-Dist: typing-extensions ==4.8.0
Requires-Dist: uvicorn ==0.23.2
Requires-Dist: pandas ==2.0.3
Requires-Dist: python-json-logger ==2.0.1
Requires-Dist: python-multipart ==0.0.6
Requires-Dist: psycopg2-binary ==2.9.7
Requires-Dist: boto3 ==1.33.8
Requires-Dist: redis ==5.0.1
Requires-Dist: numpy ==1.23.5
Requires-Dist: openai ==1.14.1
Requires-Dist: pgvector ==0.2.5
Requires-Dist: docx2txt ==0.8
Requires-Dist: pypdf ==4.1.0
Requires-Dist: langchain ==0.1.16
Requires-Dist: langchain-community ==0.0.32
Requires-Dist: langchain-core ==0.1.42
Requires-Dist: langchain-text-splitters ==0.0.1
Requires-Dist: langsmith ==0.1.45
Requires-Dist: sqlalchemy ==2.0.29
Requires-Dist: tiktoken ==0.6.0
Requires-Dist: tika ==2.6.0
Requires-Dist: tenacity ==8.3.0
Requires-Dist: asyncpg ==0.29.0
Requires-Dist: redisearch
Requires-Dist: openpyxl ==3.0.0
